{
    "example_source": [
        "x我还",
        "澄清",
        "了",
        "在该",
        "会议上",
        "提出的",
        "若干",
        "事项",
        "。"
    ],
    "example_target": [
        "<s>",
        "xi",
        "xwas",
        "xable",
        "xto",
        "xprovide",
        "xclarification",
        "xon",
        "xsome",
        "xof",
        "xthe",
        "xmatters",
        "xwhich",
        "xwere",
        "xraised",
        "xat",
        "xthat",
        "xmeeting",
        ".",
        "</s>"
    ],
    "hypotheses": [
        {
            "hypothesis": [
                "xi",
                "xwould",
                "xalso",
                "xlike",
                "xto",
                "xexpress",
                "xthe",
                "xsecretary",
                "-",
                "general",
                "xof",
                "xthe",
                "xsecretary",
                "-",
                "general",
                "."
            ],
            "score": -22.48832130432129
        },
        {
            "hypothesis": [
                "xi",
                "xwould",
                "xalso",
                "xlike",
                "xto",
                "xthe",
                "xsecretary",
                "-",
                "general",
                "xfor",
                "xthe",
                "xsecretary",
                "-",
                "general",
                "'",
                "s",
                "xreport",
                "."
            ],
            "score": -25.16750717163086
        },
        {
            "hypothesis": [
                "xi",
                "xwould",
                "xalso",
                "xlike",
                "xto",
                "xthe",
                "xsecretary",
                "-",
                "general",
                "xof",
                "xthe",
                "xsecretary",
                "-",
                "general",
                "'",
                "s",
                "xreport",
                "."
            ],
            "score": -25.190204620361328
        },
        {
            "hypothesis": [
                "xi",
                "xwould",
                "xalso",
                "xlike",
                "xto",
                "xthe",
                "xsecretary",
                "-",
                "general",
                "xfor",
                "xthe",
                "xsecretary",
                "-",
                "general",
                "xof",
                "xthe",
                "xsecretary",
                "-",
                "general",
                "."
            ],
            "score": -25.78572654724121
        },
        {
            "hypothesis": [
                "xi",
                "xwould",
                "xalso",
                "xlike",
                "xto",
                "xthe",
                "xsecretary",
                "-",
                "general",
                "xof",
                "xthe",
                "xsecretary",
                "-",
                "general",
                "xof",
                "xthe",
                "xsecretary",
                "-",
                "general",
                "."
            ],
            "score": -25.81769561767578
        },
        {
            "hypothesis": [
                "xi",
                "xwould",
                "xalso",
                "xlike",
                "xto",
                "xmake",
                "xthe",
                "xsecretary",
                "-",
                "general",
                "xof",
                "xthe",
                "xsecretary",
                "-",
                "general",
                "'",
                "s",
                "xreport",
                "."
            ],
            "score": -26.797679901123047
        },
        {
            "hypothesis": [
                "xi",
                "xwould",
                "xalso",
                "xlike",
                "xto",
                "xthe",
                "xsecretary",
                "-",
                "general",
                "xof",
                "xthe",
                "xsecretary",
                "-",
                "general",
                "xof",
                "xthe",
                "xsecretary",
                "-",
                "general",
                "'",
                "s",
                "xreport",
                "."
            ],
            "score": -30.66518211364746
        },
        {
            "hypothesis": [
                "xi",
                "xwould",
                "xalso",
                "xlike",
                "xto",
                "xthe",
                "xsecretary",
                "-",
                "general",
                "xfor",
                "xthe",
                "xsecretary",
                "-",
                "general",
                "xof",
                "xthe",
                "xsecretary",
                "-",
                "general",
                "'",
                "s",
                "xreport",
                "."
            ],
            "score": -30.79250144958496
        },
        {
            "hypothesis": [
                "xi",
                "xwould",
                "xalso",
                "xlike",
                "xto",
                "xthe",
                "xsecretary",
                "-",
                "general",
                "xof",
                "xthe",
                "xsecretary",
                "-",
                "general",
                "xof",
                "xthe",
                "xsecretary",
                "-",
                "general",
                "'",
                "s",
                "xmeeting",
                "."
            ],
            "score": -31.578569412231445
        },
        {
            "hypothesis": [
                "xi",
                "xwould",
                "xalso",
                "xlike",
                "xto",
                "xthe",
                "xsecretary",
                "-",
                "general",
                "xfor",
                "xthe",
                "xsecretary",
                "-",
                "general",
                "xof",
                "xthe",
                "xsecretary",
                "-",
                "general",
                "'",
                "s",
                "xmeeting",
                "."
            ],
            "score": -31.689922332763672
        }
    ],
    "diagnostic_info": "eyJ0IjogIjIwMjQtMTAtMjhUMTU6MDc6MDQuNDQ4MzIzIiwgImgiOiAiU0VBTkdVQU4tTkIxIiwgInUiOiAiU2VhbiJ9"
}